[{"batter":"N Pooran","team":"MI Emirates","cais":304.69,"raw_sr":170.19,"runs":354,"balls":208,"matches":10,"rank":1},{"batter":"Sikandar Raza","team":"Dubai Capitals","cais":257.43,"raw_sr":134.33,"runs":313,"balls":233,"matches":11,"rank":2},{"batter":"SO Hetmyer","team":"Gulf Giants","cais":241.64,"raw_sr":141.61,"runs":228,"balls":161,"matches":12,"rank":3},{"batter":"SW Billings","team":"Dubai Capitals","cais":237.53,"raw_sr":140.35,"runs":320,"balls":228,"matches":12,"rank":4},{"batter":"MDKJ Perera","team":"MI Emirates","cais":228.54,"raw_sr":157.28,"runs":335,"balls":213,"matches":10,"rank":5},{"batter":"AD Hales","team":"Desert Vipers","cais":213.08,"raw_sr":141.0,"runs":282,"balls":200,"matches":10,"rank":6},{"batter":"J Charles","team":"Sharjah Warriors","cais":212.78,"raw_sr":136.47,"runs":232,"balls":170,"matches":8,"rank":7},{"batter":"Waseem Muhammad","team":"MI Emirates","cais":207.13,"raw_sr":147.93,"runs":321,"balls":217,"matches":12,"rank":8},{"batter":"MS Pepper","team":"Abu Dhabi Knight Riders","cais":199.01,"raw_sr":141.36,"runs":229,"balls":162,"matches":10,"rank":9},{"batter":"CA Lynn","team":"Gulf Giants","cais":197.08,"raw_sr":127.35,"runs":284,"balls":223,"matches":10,"rank":10},{"batter":"SR Hain","team":"Abu Dhabi Knight Riders","cais":193.73,"raw_sr":117.34,"runs":203,"balls":173,"matches":10,"rank":11},{"batter":"ADS Fletcher","team":"MI Emirates","cais":193.49,"raw_sr":122.64,"runs":260,"balls":212,"matches":10,"rank":12},{"batter":"A Sharafu","team":"Abu Dhabi Knight Riders","cais":184.18,"raw_sr":120.22,"runs":220,"balls":183,"matches":11,"rank":13},{"batter":"JM Vince","team":"Gulf Giants","cais":183.85,"raw_sr":120.27,"runs":356,"balls":296,"matches":12,"rank":14},{"batter":"JM Cox","team":"Gulf Giants","cais":176.35,"raw_sr":113.16,"runs":215,"balls":190,"matches":12,"rank":15}]