[{"bowler":"RJ Gleeson","runs_conceded":458,"wickets":27,"matches":15,"balls":338,"economy":8.13,"avg":16.96},{"bowler":"CP Wood","runs_conceded":481,"wickets":26,"matches":16,"balls":364,"economy":7.93,"avg":18.5},{"bowler":"GLS Scrimshaw","runs_conceded":520,"wickets":24,"matches":15,"balls":346,"economy":9.02,"avg":21.67},{"bowler":"JB Lintott","runs_conceded":454,"wickets":24,"matches":15,"balls":327,"economy":8.33,"avg":18.92},{"bowler":"Naveen-ul-Haq","runs_conceded":379,"wickets":24,"matches":14,"balls":306,"economy":7.43,"avg":15.79},{"bowler":"BTJ Wheal","runs_conceded":382,"wickets":23,"matches":13,"balls":262,"economy":8.75,"avg":16.61},{"bowler":"JK Fuller","runs_conceded":439,"wickets":23,"matches":16,"balls":338,"economy":7.79,"avg":19.09},{"bowler":"MG Hogan","runs_conceded":330,"wickets":22,"matches":11,"balls":246,"economy":8.05,"avg":15.0},{"bowler":"BGF Green","runs_conceded":453,"wickets":21,"matches":16,"balls":304,"economy":8.94,"avg":21.57},{"bowler":"CF Parkinson","runs_conceded":400,"wickets":21,"matches":14,"balls":330,"economy":7.27,"avg":19.05},{"bowler":"AJ Tye","runs_conceded":311,"wickets":21,"matches":10,"balls":210,"economy":8.89,"avg":14.81},{"bowler":"JA Thompson","runs_conceded":468,"wickets":20,"matches":15,"balls":286,"economy":9.82,"avg":23.4},{"bowler":"LA Dawson","runs_conceded":413,"wickets":20,"matches":16,"balls":349,"economy":7.1,"avg":20.65},{"bowler":"JT Ball","runs_conceded":229,"wickets":20,"matches":7,"balls":145,"economy":9.48,"avg":11.45},{"bowler":"DA Payne","runs_conceded":256,"wickets":20,"matches":9,"balls":197,"economy":7.8,"avg":12.8},{"bowler":"CR Brathwaite","runs_conceded":441,"wickets":19,"matches":15,"balls":283,"economy":9.35,"avg":23.21},{"bowler":"CJ Jordan","runs_conceded":374,"wickets":19,"matches":13,"balls":284,"economy":7.9,"avg":19.68},{"bowler":"NT Ellis","runs_conceded":322,"wickets":19,"matches":13,"balls":279,"economy":6.92,"avg":16.95},{"bowler":"Rehan Ahmed","runs_conceded":385,"wickets":19,"matches":14,"balls":313,"economy":7.38,"avg":20.26},{"bowler":"PM Siddle","runs_conceded":296,"wickets":18,"matches":11,"balls":218,"economy":8.15,"avg":16.44},{"bowler":"BWM Mike","runs_conceded":364,"wickets":18,"matches":14,"balls":249,"economy":8.77,"avg":20.22},{"bowler":"BW Sanderson","runs_conceded":441,"wickets":18,"matches":13,"balls":285,"economy":9.28,"avg":24.5},{"bowler":"SR Harmer","runs_conceded":362,"wickets":18,"matches":14,"balls":322,"economy":6.75,"avg":20.11},{"bowler":"TS Mills","runs_conceded":329,"wickets":18,"matches":9,"balls":205,"economy":9.63,"avg":18.28},{"bowler":"DR Briggs","runs_conceded":404,"wickets":18,"matches":14,"balls":282,"economy":8.6,"avg":22.44},{"bowler":"TW Hartley","runs_conceded":439,"wickets":18,"matches":16,"balls":313,"economy":8.42,"avg":24.39},{"bowler":"BA Raine","runs_conceded":317,"wickets":18,"matches":14,"balls":262,"economy":7.26,"avg":17.61},{"bowler":"SR Patel","runs_conceded":360,"wickets":17,"matches":13,"balls":282,"economy":7.66,"avg":21.18},{"bowler":"MH McKiernan","runs_conceded":433,"wickets":17,"matches":14,"balls":289,"economy":8.99,"avg":25.47},{"bowler":"MK Andersson","runs_conceded":357,"wickets":17,"matches":12,"balls":230,"economy":9.31,"avg":21.0},{"bowler":"CN Miles","runs_conceded":391,"wickets":17,"matches":14,"balls":255,"economy":9.2,"avg":23.0},{"bowler":"H Kerr","runs_conceded":360,"wickets":16,"matches":13,"balls":237,"economy":9.11,"avg":22.5},{"bowler":"ML Revis","runs_conceded":405,"wickets":16,"matches":16,"balls":248,"economy":9.8,"avg":25.31},{"bowler":"DJ Lamb","runs_conceded":319,"wickets":16,"matches":13,"balls":203,"economy":9.43,"avg":19.94},{"bowler":"MG Neser","runs_conceded":246,"wickets":15,"matches":9,"balls":186,"economy":7.94,"avg":16.4},{"bowler":"MJJ Critchley","runs_conceded":266,"wickets":15,"matches":10,"balls":208,"economy":7.67,"avg":17.73},{"bowler":"L Wood","runs_conceded":391,"wickets":15,"matches":13,"balls":274,"economy":8.56,"avg":26.06},{"bowler":"P Sisodiya","runs_conceded":384,"wickets":15,"matches":13,"balls":276,"economy":8.35,"avg":25.6},{"bowler":"L Gregory","runs_conceded":304,"wickets":15,"matches":15,"balls":205,"economy":8.9,"avg":20.27},{"bowler":"OC McCoy","runs_conceded":164,"wickets":15,"matches":5,"balls":118,"economy":8.34,"avg":10.93},{"bowler":"RJW Topley","runs_conceded":306,"wickets":15,"matches":10,"balls":216,"economy":8.5,"avg":20.4},{"bowler":"SP Narine","runs_conceded":318,"wickets":15,"matches":13,"balls":314,"economy":6.08,"avg":21.2},{"bowler":"TAI Taylor","runs_conceded":390,"wickets":15,"matches":13,"balls":254,"economy":9.21,"avg":26.0},{"bowler":"FJ Heldreich","runs_conceded":353,"wickets":15,"matches":12,"balls":223,"economy":9.5,"avg":23.53},{"bowler":"JH Davey","runs_conceded":313,"wickets":15,"matches":11,"balls":219,"economy":8.58,"avg":20.87},{"bowler":"PR Brown","runs_conceded":361,"wickets":14,"matches":12,"balls":234,"economy":9.26,"avg":25.78},{"bowler":"OP Stone","runs_conceded":277,"wickets":14,"matches":10,"balls":222,"economy":7.49,"avg":19.78},{"bowler":"G Stewart","runs_conceded":331,"wickets":14,"matches":11,"balls":206,"economy":9.64,"avg":23.64},{"bowler":"FJ Klaassen","runs_conceded":405,"wickets":14,"matches":13,"balls":281,"economy":8.65,"avg":28.93},{"bowler":"Qais Ahmad","runs_conceded":404,"wickets":14,"matches":14,"balls":330,"economy":7.35,"avg":28.86},{"bowler":"DR Sams","runs_conceded":399,"wickets":14,"matches":12,"balls":265,"economy":9.03,"avg":28.5},{"bowler":"MRJ Watt","runs_conceded":484,"wickets":14,"matches":15,"balls":349,"economy":8.32,"avg":34.57},{"bowler":"ST Finn","runs_conceded":386,"wickets":14,"matches":14,"balls":247,"economy":9.38,"avg":27.57},{"bowler":"CJ Green","runs_conceded":383,"wickets":14,"matches":14,"balls":280,"economy":8.21,"avg":27.36},{"bowler":"TMJ Smith","runs_conceded":264,"wickets":14,"matches":12,"balls":204,"economy":7.76,"avg":18.86},{"bowler":"RS Bopara","runs_conceded":292,"wickets":13,"matches":13,"balls":233,"economy":7.52,"avg":22.46},{"bowler":"SJ Cook","runs_conceded":372,"wickets":13,"matches":14,"balls":274,"economy":8.15,"avg":28.61},{"bowler":"AAP Atkinson","runs_conceded":159,"wickets":13,"matches":6,"balls":123,"economy":7.76,"avg":12.23},{"bowler":"GF Linde","runs_conceded":341,"wickets":13,"matches":13,"balls":258,"economy":7.93,"avg":26.23},{"bowler":"GG White","runs_conceded":316,"wickets":13,"matches":12,"balls":234,"economy":8.1,"avg":24.31},{"bowler":"LJ Fletcher","runs_conceded":305,"wickets":13,"matches":9,"balls":195,"economy":9.38,"avg":23.46},{"bowler":"L Trevaskis","runs_conceded":391,"wickets":13,"matches":13,"balls":286,"economy":8.2,"avg":30.07},{"bowler":"DJ Willey","runs_conceded":246,"wickets":13,"matches":9,"balls":186,"economy":7.94,"avg":18.92},{"bowler":"DMW Rawlins","runs_conceded":318,"wickets":13,"matches":14,"balls":246,"economy":7.76,"avg":24.46},{"bowler":"MW Parkinson","runs_conceded":298,"wickets":13,"matches":12,"balls":242,"economy":7.39,"avg":22.92},{"bowler":"BAC Howell","runs_conceded":327,"wickets":12,"matches":12,"balls":276,"economy":7.11,"avg":27.25},{"bowler":"BMJ Allison","runs_conceded":327,"wickets":12,"matches":13,"balls":209,"economy":9.39,"avg":27.25},{"bowler":"P Coughlin","runs_conceded":390,"wickets":12,"matches":13,"balls":247,"economy":9.47,"avg":32.5},{"bowler":"JDS Neesham","runs_conceded":311,"wickets":12,"matches":10,"balls":199,"economy":9.38,"avg":25.91},{"bowler":"JJ Cobb","runs_conceded":210,"wickets":12,"matches":11,"balls":178,"economy":7.08,"avg":17.5},{"bowler":"JP Behrendorff","runs_conceded":329,"wickets":12,"matches":11,"balls":239,"economy":8.26,"avg":27.41},{"bowler":"MS Crane","runs_conceded":391,"wickets":12,"matches":14,"balls":252,"economy":9.31,"avg":32.58},{"bowler":"SM Curran","runs_conceded":123,"wickets":11,"matches":5,"balls":97,"economy":7.61,"avg":11.18},{"bowler":"DA Douthwaite","runs_conceded":382,"wickets":11,"matches":13,"balls":259,"economy":8.85,"avg":34.72},{"bowler":"RE van der Merwe","runs_conceded":312,"wickets":11,"matches":16,"balls":246,"economy":7.61,"avg":28.36},{"bowler":"BL D'Oliveira","runs_conceded":213,"wickets":11,"matches":10,"balls":174,"economy":7.34,"avg":19.36},{"bowler":"ZJ Chappell","runs_conceded":126,"wickets":11,"matches":6,"balls":103,"economy":7.34,"avg":11.45},{"bowler":"S Conners","runs_conceded":284,"wickets":10,"matches":11,"balls":148,"economy":11.51,"avg":28.4},{"bowler":"DC Drakes","runs_conceded":163,"wickets":10,"matches":5,"balls":114,"economy":8.58,"avg":16.3},{"bowler":"C Overton","runs_conceded":137,"wickets":10,"matches":6,"balls":96,"economy":8.56,"avg":13.7},{"bowler":"TS Roland-Jones","runs_conceded":175,"wickets":10,"matches":6,"balls":126,"economy":8.33,"avg":17.5}]