{"name":"Suyash Sharma","competition":"ipl","bowling":{"wickets":25,"matches":36,"balls":749,"runs_conceded":1063,"economy":8.52,"average":42.52},"bowling_seasons":[{"season":2023,"runs":317,"wickets":10,"balls":234,"matches":11,"economy":8.13},{"season":2024,"runs":50,"wickets":0,"balls":24,"matches":2,"economy":12.5},{"season":2025,"runs":433,"wickets":8,"balls":300,"matches":14,"economy":8.66},{"season":2026,"runs":263,"wickets":7,"balls":191,"matches":9,"economy":8.26}],"cais_bowling":{"score":13.46,"rank":236,"total":254}}