[{"batter":"JM Vince","total_runs":424,"matches":10,"dismissals":8,"average":53.0,"balls_faced":297,"SR":142.76},{"batter":"BM Duckett","total_runs":269,"matches":7,"dismissals":4,"average":67.25,"balls_faced":157,"SR":171.34},{"batter":"PD Salt","total_runs":228,"matches":8,"dismissals":8,"average":28.5,"balls_faced":153,"SR":149.02},{"batter":"N Pooran","total_runs":227,"matches":7,"dismissals":5,"average":45.4,"balls_faced":151,"SR":150.33},{"batter":"JM Cox","total_runs":214,"matches":7,"dismissals":5,"average":42.8,"balls_faced":149,"SR":143.62},{"batter":"T Banton","total_runs":211,"matches":8,"dismissals":8,"average":26.38,"balls_faced":142,"SR":148.59},{"batter":"AD Hales","total_runs":204,"matches":8,"dismissals":7,"average":29.14,"balls_faced":156,"SR":130.77},{"batter":"SM Curran","total_runs":201,"matches":6,"dismissals":5,"average":40.2,"balls_faced":122,"SR":164.75}]