[{"batter":"BJ Bennett","total_runs":606,"matches":11,"dismissals":8,"average":75.75,"balls_faced":390,"SR":155.38},{"batter":"J Baker","total_runs":559,"matches":12,"dismissals":11,"average":50.82,"balls_faced":394,"SR":141.88},{"batter":"A Sharafu","total_runs":388,"matches":9,"dismissals":8,"average":48.5,"balls_faced":295,"SR":131.53},{"batter":"Sahibzada Farhan","total_runs":383,"matches":6,"dismissals":5,"average":76.6,"balls_faced":239,"SR":160.25},{"batter":"SV Samson","total_runs":321,"matches":5,"dismissals":4,"average":80.25,"balls_faced":161,"SR":199.38},{"batter":"Ishan Kishan","total_runs":317,"matches":9,"dismissals":9,"average":35.22,"balls_faced":164,"SR":193.29},{"batter":"T Marumani","total_runs":309,"matches":11,"dismissals":10,"average":30.9,"balls_faced":229,"SR":134.93},{"batter":"YS Samra","total_runs":298,"matches":8,"dismissals":6,"average":49.67,"balls_faced":158,"SR":188.61},{"batter":"FH Allen","total_runs":297,"matches":7,"dismissals":5,"average":59.4,"balls_faced":147,"SR":202.04},{"batter":"DS Airee","total_runs":285,"matches":10,"dismissals":7,"average":40.71,"balls_faced":212,"SR":134.43},{"batter":"K Bhurtel","total_runs":285,"matches":10,"dismissals":11,"average":25.91,"balls_faced":242,"SR":117.77},{"batter":"AK Markram","total_runs":281,"matches":7,"dismissals":5,"average":56.2,"balls_faced":165,"SR":170.3},{"batter":"Sikandar Raza","total_runs":280,"matches":11,"dismissals":9,"average":31.11,"balls_faced":179,"SR":156.42},{"batter":"JG Bethell","total_runs":280,"matches":8,"dismissals":8,"average":35.0,"balls_faced":184,"SR":152.17},{"batter":"P Baron","total_runs":275,"matches":6,"dismissals":8,"average":34.38,"balls_faced":201,"SR":136.82},{"batter":"JN Frylinck","total_runs":273,"matches":9,"dismissals":8,"average":34.12,"balls_faced":172,"SR":158.72},{"batter":"Aasif Sheikh","total_runs":266,"matches":10,"dismissals":10,"average":26.6,"balls_faced":214,"SR":124.3},{"batter":"TL Seifert","total_runs":261,"matches":7,"dismissals":6,"average":43.5,"balls_faced":154,"SR":169.48},{"batter":"JJ Smit","total_runs":259,"matches":8,"dismissals":6,"average":43.17,"balls_faced":158,"SR":163.92},{"batter":"Waseem Muhammad","total_runs":252,"matches":9,"dismissals":8,"average":31.5,"balls_faced":195,"SR":129.23},{"batter":"MP O'Dowd","total_runs":249,"matches":8,"dismissals":6,"average":41.5,"balls_faced":196,"SR":127.04},{"batter":"SO Hetmyer","total_runs":248,"matches":7,"dismissals":6,"average":41.33,"balls_faced":133,"SR":186.47},{"batter":"AR Naidoo","total_runs":243,"matches":10,"dismissals":6,"average":40.5,"balls_faced":192,"SR":126.56},{"batter":"SA Yadav","total_runs":242,"matches":9,"dismissals":9,"average":26.89,"balls_faced":177,"SR":136.72},{"batter":"SA Edwards","total_runs":236,"matches":8,"dismissals":4,"average":59.0,"balls_faced":179,"SR":131.84},{"batter":"HC Brook","total_runs":235,"matches":8,"dismissals":8,"average":29.38,"balls_faced":147,"SR":159.86},{"batter":"S Dube","total_runs":235,"matches":8,"dismissals":3,"average":78.33,"balls_faced":139,"SR":169.06},{"batter":"L Steenkamp","total_runs":226,"matches":9,"dismissals":9,"average":25.11,"balls_faced":162,"SR":139.51},{"batter":"WG Jacks","total_runs":226,"matches":8,"dismissals":4,"average":56.5,"balls_faced":128,"SR":176.56},{"batter":"RK Paudel","total_runs":217,"matches":10,"dismissals":9,"average":24.11,"balls_faced":178,"SR":121.91},{"batter":"SD Hope","total_runs":217,"matches":7,"dismissals":6,"average":36.17,"balls_faced":166,"SR":130.72},{"batter":"HH Pandya","total_runs":217,"matches":9,"dismissals":9,"average":24.11,"balls_faced":135,"SR":160.74},{"batter":"HG Munsey","total_runs":216,"matches":7,"dismissals":7,"average":30.86,"balls_faced":176,"SR":122.73},{"batter":"YSD Seneveratne","total_runs":215,"matches":6,"dismissals":2,"average":107.5,"balls_faced":171,"SR":125.73},{"batter":"II Selemani","total_runs":214,"matches":5,"dismissals":5,"average":42.8,"balls_faced":118,"SR":181.36},{"batter":"P Nissanka","total_runs":211,"matches":7,"dismissals":6,"average":35.17,"balls_faced":143,"SR":147.55},{"batter":"RD Berrington","total_runs":210,"matches":7,"dismissals":6,"average":35.0,"balls_faced":151,"SR":139.07},{"batter":"Tilak Varma","total_runs":207,"matches":9,"dismissals":7,"average":29.57,"balls_faced":134,"SR":154.48},{"batter":"Arun Yadav","total_runs":206,"matches":9,"dismissals":8,"average":25.75,"balls_faced":159,"SR":129.56},{"batter":"SL Verma","total_runs":206,"matches":5,"dismissals":4,"average":51.5,"balls_faced":134,"SR":153.73},{"batter":"Sami Sohail","total_runs":205,"matches":9,"dismissals":8,"average":25.62,"balls_faced":161,"SR":127.33},{"batter":"P Rathnayake","total_runs":205,"matches":7,"dismissals":6,"average":34.17,"balls_faced":133,"SR":154.14},{"batter":"MG Erasmus","total_runs":201,"matches":8,"dismissals":8,"average":25.12,"balls_faced":144,"SR":139.58},{"batter":"Esam Rahman","total_runs":200,"matches":6,"dismissals":6,"average":33.33,"balls_faced":160,"SR":125.0}]