[{"batter":"Shahid Afridi","runs":91,"balls":46,"matches":6,"SR":197.83},{"batter":"CH Gayle","runs":117,"balls":60,"matches":2,"SR":195.0},{"batter":"Yuvraj Singh","runs":148,"balls":76,"matches":5,"SR":194.74},{"batter":"Mohammad Ashraful","runs":87,"balls":48,"matches":5,"SR":181.25},{"batter":"CD McMillan","runs":163,"balls":90,"matches":5,"SR":181.11},{"batter":"J Mubarak","runs":105,"balls":62,"matches":4,"SR":169.35},{"batter":"KP Pietersen","runs":178,"balls":110,"matches":5,"SR":161.82},{"batter":"ST Jayasuriya","runs":154,"balls":96,"matches":5,"SR":160.42},{"batter":"JDP Oram","runs":92,"balls":60,"matches":5,"SR":153.33},{"batter":"DPMD Jayawardene","runs":159,"balls":104,"matches":5,"SR":152.88},{"batter":"AC Gilchrist","runs":169,"balls":112,"matches":6,"SR":150.89},{"batter":"A Symonds","runs":107,"balls":71,"matches":4,"SR":150.7},{"batter":"Imran Nazir","runs":147,"balls":98,"matches":7,"SR":150.0},{"batter":"Junaid Siddique","runs":71,"balls":49,"matches":1,"SR":144.9},{"batter":"ML Hayden","runs":265,"balls":183,"matches":6,"SR":144.81},{"batter":"RG Sharma","runs":88,"balls":61,"matches":3,"SR":144.26},{"batter":"HH Gibbs","runs":110,"balls":77,"matches":3,"SR":142.86},{"batter":"DL Maddy","runs":113,"balls":80,"matches":4,"SR":141.25},{"batter":"Misbah-ul-Haq","runs":218,"balls":156,"matches":7,"SR":139.74},{"batter":"JA Morkel","runs":120,"balls":86,"matches":3,"SR":139.53},{"batter":"JM Kemp","runs":173,"balls":124,"matches":5,"SR":139.52},{"batter":"LRPL Taylor","runs":118,"balls":85,"matches":5,"SR":138.82},{"batter":"V Sehwag","runs":133,"balls":96,"matches":5,"SR":138.54},{"batter":"BJ Hodge","runs":82,"balls":61,"matches":3,"SR":134.43},{"batter":"PD Collingwood","runs":86,"balls":65,"matches":5,"SR":132.31},{"batter":"A Flintoff","runs":70,"balls":53,"matches":5,"SR":132.08},{"batter":"G Gambhir","runs":227,"balls":175,"matches":6,"SR":129.71},{"batter":"Aftab Ahmed","runs":162,"balls":125,"matches":5,"SR":129.6},{"batter":"MS Dhoni","runs":154,"balls":120,"matches":6,"SR":128.33},{"batter":"BRM Taylor","runs":107,"balls":84,"matches":2,"SR":127.38},{"batter":"OA Shah","runs":103,"balls":81,"matches":5,"SR":127.16},{"batter":"Mohammad Hafeez","runs":99,"balls":78,"matches":6,"SR":126.92},{"batter":"Shoaib Malik","runs":195,"balls":154,"matches":7,"SR":126.62},{"batter":"WU Tharanga","runs":74,"balls":60,"matches":5,"SR":123.33},{"batter":"TM Dilshan","runs":65,"balls":53,"matches":4,"SR":122.64},{"batter":"BB McCullum","runs":139,"balls":114,"matches":6,"SR":121.93},{"batter":"GC Smith","runs":94,"balls":78,"matches":5,"SR":120.51},{"batter":"VS Solanki","runs":67,"balls":56,"matches":2,"SR":119.64},{"batter":"Shakib Al Hasan","runs":67,"balls":56,"matches":5,"SR":119.64},{"batter":"SB Styris","runs":70,"balls":59,"matches":5,"SR":118.64},{"batter":"LPC Silva","runs":70,"balls":61,"matches":5,"SR":114.75},{"batter":"RV Uthappa","runs":113,"balls":100,"matches":6,"SR":113.0},{"batter":"MJ Prior","runs":69,"balls":62,"matches":3,"SR":111.29},{"batter":"MEK Hussey","runs":65,"balls":60,"matches":3,"SR":108.33},{"batter":"Younis Khan","runs":127,"balls":118,"matches":7,"SR":107.63},{"batter":"PG Fulton","runs":77,"balls":73,"matches":5,"SR":105.48},{"batter":"KC Sangakkara","runs":104,"balls":99,"matches":5,"SR":105.05},{"batter":"L Vincent","runs":117,"balls":116,"matches":6,"SR":100.86},{"batter":"DS Smith","runs":86,"balls":86,"matches":2,"SR":100.0},{"batter":"MV Boucher","runs":88,"balls":93,"matches":3,"SR":94.62},{"batter":"RT Ponting","runs":61,"balls":65,"matches":4,"SR":93.85},{"batter":"Salman Butt","runs":74,"balls":105,"matches":5,"SR":70.48}]